sumologic_collectd_metrics/__init__.py
sumologic_collectd_metrics/metrics_batcher.py
sumologic_collectd_metrics/metrics_buffer.py
sumologic_collectd_metrics/metrics_config.py
sumologic_collectd_metrics/metrics_converter.py
sumologic_collectd_metrics/metrics_sender.py
sumologic_collectd_metrics/metrics_util.py
sumologic_collectd_metrics/metrics_writer.py
sumologic_collectd_metrics/timer.py
sumologic_collectd_metrics-4.1.1.dist-info/LICENSE
sumologic_collectd_metrics-4.1.1.dist-info/METADATA
sumologic_collectd_metrics-4.1.1.dist-info/WHEEL
sumologic_collectd_metrics-4.1.1.dist-info/top_level.txt
sumologic_collectd_metrics-4.1.1.dist-info/RECORD
