Metadata-Version: 2.1
Name: sumologic-collectd-metrics
Version: 4.1.1
Summary: A collectd output plugin to send Carbon 2.0-formatted metrics to Sumo Logic.
Home-page: https://github.com/SumoLogic/sumologic-collectd-plugin
Author: Sumo Logic
Author-email: support@sumologic.com
License: Apache Software License, Version 2.0
Platform: UNKNOWN
License-File: LICENSE
Requires-Dist: requests
Requires-Dist: retry
